flake8_future_import.py
flake8_future_import-0.4.7.dist-info/LICENSE
flake8_future_import-0.4.7.dist-info/METADATA
flake8_future_import-0.4.7.dist-info/WHEEL
flake8_future_import-0.4.7.dist-info/entry_points.txt
flake8_future_import-0.4.7.dist-info/top_level.txt
flake8_future_import-0.4.7.dist-info/RECORD
