Metadata-Version: 2.1
Name: flake8-future-import
Version: 0.4.7
Summary: __future__ import checker, plugin for flake8
Home-page: https://github.com/xZise/flake8-future-import
Author: Fabian Neundorf
Author-email: Fabian Neundorf <CommodoreFabianus@gmx.de>
License: MIT License
Project-URL: Homepage, https://github.com/xZise/flake8-future-import
Project-URL: Bug Tracker, https://github.com/xZise/flake8-future-import/issues
Keywords: flake8,import,future
Classifier: Development Status :: 3 - Alpha
Classifier: Environment :: Console
Classifier: Framework :: Flake8
Classifier: Intended Audience :: Developers
Classifier: License :: OSI Approved :: MIT License
Classifier: Operating System :: OS Independent
Classifier: Programming Language :: Python
Classifier: Programming Language :: Python :: 3.6
Classifier: Programming Language :: Python :: 3.7
Classifier: Programming Language :: Python :: 3.8
Classifier: Programming Language :: Python :: 3.9
Classifier: Programming Language :: Python :: 3.10
Classifier: Topic :: Software Development :: Libraries :: Python Modules
Requires-Python: >=3.6
License-File: LICENSE
Requires-Dist: flake8
